xl_word/__init__.py
xl_word/__main__.py
xl_word/document.py
xl_word/h.docx
xl_word/mixins.py
xl_word/sheet.py
xl_word/v.docx
xl_word/word_file.py
xl_word/compiler/__init__.py
xl_word/compiler/processors/__init__.py
xl_word/compiler/processors/base.py
xl_word/compiler/processors/directive.py
xl_word/compiler/processors/pager.py
xl_word/compiler/processors/paragraph.py
xl_word/compiler/processors/style.py
xl_word/compiler/processors/table.py
xl_word/tool/__init__.py
xl_word/tool/build.bat
xl_word/tool/document.xml
xl_word/tool/gui.py
xl_word/tool/h.docx
xl_word/tool/tool.spec
xl_word/tool/utility.py
xl_word/tool/v.docx
xl_word/utils/fake_zip.py
xl_word/utils/tree.py
xl_word-0.6.7.dist-info/METADATA
xl_word-0.6.7.dist-info/WHEEL
xl_word-0.6.7.dist-info/RECORD
