Metadata-Version: 2.1
Name: xl-word
Version: 0.6.7
Summary: generate word documents in a sexy way
Project-URL: Homepage, https://github.com/inspirare6/xl-word
Project-URL: Bug Tracker, https://github.com/inspirare6/xl-word/issues
Author-email: inspirare6 <inspirare6@163.com>
Classifier: License :: OSI Approved :: MIT License
Classifier: Operating System :: OS Independent
Classifier: Programming Language :: Python :: 3
Requires-Python: >=3.7
Requires-Dist: cssselect==1.2.0
Requires-Dist: jinja2==3.1.2
Requires-Dist: lxml==4.9.2
